arh/__init__.py
arh/arh.py
arh-1.1.0.dist-info/METADATA
arh-1.1.0.dist-info/WHEEL
arh-1.1.0.dist-info/top_level.txt
arh-1.1.0.dist-info/RECORD
